kripfunc/__init__.py
kripfunc/sqlite.py
kripfunc-0.0.1.dist-info/LICENSE
kripfunc-0.0.1.dist-info/METADATA
kripfunc-0.0.1.dist-info/WHEEL
kripfunc-0.0.1.dist-info/top_level.txt
kripfunc-0.0.1.dist-info/RECORD
