Metadata-Version: 2.1
Name: kripfunc
Version: 0.0.1
Summary: A random function set made by vinkami
Home-page: https://github.com/vinkami/kripfunc
Author: vinkami
Author-email: vinkami.krip@gmail.com
License: UNKNOWN
Platform: UNKNOWN
Classifier: Programming Language :: Python :: 3
Classifier: License :: OSI Approved :: MIT License
Classifier: Operating System :: OS Independent
Classifier: Development Status :: 5 - Production/Stable
Requires-Python: >=3
License-File: LICENSE
